kirami_plugin_hitokoto-0.1.0.dist-info/METADATA
kirami_plugin_hitokoto-0.1.0.dist-info/WHEEL
kirami_plugin_hitokoto-0.1.0.dist-info/licenses/LICENSE
kirami_plugin_hitokoto/__init__.py
kirami_plugin_hitokoto/service.toml
kirami_plugin_hitokoto-0.1.0.dist-info/RECORD
