Metadata-Version: 2.1
Name: kirami-plugin-hitokoto
Version: 0.1.0
Summary: 总有一句话能打动你的心
Author-Email: Komorebi <mute231010@gmail.com>
License: MIT
Project-URL: Homepage, https://github.com/KomoriDev/kirami-plugin-hitokoto
Project-URL: Repository, https://github.com/KomoriDev/kirami-plugin-hitokoto
Requires-Python: >=3.10
Requires-Dist: kiramibot>=0.0.0
